zenossapi/__init__.py
zenossapi/_version.py
zenossapi/apiclient.py
zenossapi/routers/__init__.py
zenossapi/routers/cmdb.py
zenossapi/routers/device.py
zenossapi/routers/devicemanagement.py
zenossapi/routers/events.py
zenossapi/routers/incidentmanagement.py
zenossapi/routers/jobs.py
zenossapi/routers/monitor.py
zenossapi/routers/properties.py
zenossapi/routers/template.py
zenAPIClient-1.1.0.dist-info/LICENSE.md
zenAPIClient-1.1.0.dist-info/METADATA
zenAPIClient-1.1.0.dist-info/WHEEL
zenAPIClient-1.1.0.dist-info/top_level.txt
zenAPIClient-1.1.0.dist-info/RECORD
