Metadata-Version: 2.1
Name: zenAPIClient
Version: 1.1.0
Summary: Zenoss API client module
Author-email: Dan Smalley <zenapiclient@smalley.link>
License: ZenossAPIClient
Project-URL: Homepage, https://github.com/dan-smalley/zenAPIClient
Project-URL: Documentation, https://zenapiclient.readthedocs.io
Project-URL: Repository, https://github.com/dan-smalley/zenAPIClient.git
Keywords: zenoss,monitoring,api
Classifier: Intended Audience :: System Administrators
Classifier: License :: OSI Approved :: Apache Software License
Classifier: Natural Language :: English
Classifier: Programming Language :: Python :: 3
Classifier: Programming Language :: Python :: 3.12
Classifier: Topic :: System :: Monitoring
Requires-Python: >=3.6
License-File: LICENSE.md
Requires-Dist: python-dateutil >=2.6.1
Requires-Dist: requests >=2.18.1
Provides-Extra: test
Requires-Dist: pytest >=3.2.3 ; extra == 'test'
Requires-Dist: pytest-responses >=0.4.0 ; extra == 'test'
Requires-Dist: versioneer ; extra == 'test'
